flask_favicon/__init__.py
flask_favicon/flask_extension.py
flask_favicon/flask_favicon_asset.py
flask_favicon/flask_integration.py
flask_favicon/groups/abstract_favicon_group.py
flask_favicon/groups/favicon_android.py
flask_favicon/groups/favicon_apple.py
flask_favicon/groups/favicon_apple_startup.py
flask_favicon/groups/favicon_ms.py
flask_favicon/groups/favicon_standard.py
flask_favicon/groups/favicon_yandex.py
flask_favicon/templates/flask-favicon.html
flask_favicon-0.1.4.dist-info/LICENSE
flask_favicon-0.1.4.dist-info/METADATA
flask_favicon-0.1.4.dist-info/WHEEL
flask_favicon-0.1.4.dist-info/top_level.txt
flask_favicon-0.1.4.dist-info/RECORD
