Metadata-Version: 2.1
Name: flask-favicon
Version: 0.1.4
Summary: Flask extension to handle favicons.
Home-page: 
Author: Maxime Dupuis
Author-email: mdupuis@hotmail.ca
License: gpl-3.0
Project-URL: Documentation, https://maxdup.github.io/flask-favicon/
Project-URL: Github, https://github.com/maxdup/flask-favicon
Platform: any
Classifier: Environment :: Web Environment
Classifier: Framework :: Flask
Classifier: Intended Audience :: Developers
Classifier: License :: OSI Approved :: MIT License
Classifier: Operating System :: OS Independent
Classifier: Programming Language :: Python
Classifier: Programming Language :: Python :: 3
Classifier: Programming Language :: Python :: 3.7
Classifier: Programming Language :: Python :: 3.8
Classifier: Programming Language :: Python :: 3.9
Classifier: Programming Language :: Python :: 3.10
Classifier: Topic :: Internet :: WWW/HTTP :: Dynamic Content
Classifier: Topic :: Software Development :: Libraries :: Python Modules
Classifier: Topic :: System :: Archiving :: Compression
Classifier: Operating System :: Unix
Classifier: Operating System :: MacOS :: MacOS X
Classifier: Operating System :: Microsoft :: Windows
Requires-Python: >=3.7
License-File: LICENSE
Requires-Dist: Flask >=2.0
Requires-Dist: Pillow
